vvvvid_downloader/__init__.py
vvvvid_downloader/__main__.py
vvvvid_downloader/api.py
vvvvid_downloader/py.typed
vvvvid_downloader/responses.py
vvvvid_downloader/vvvvid.py
vvvvid_downloader-1.3.3.dist-info/WHEEL
vvvvid_downloader-1.3.3.dist-info/METADATA
vvvvid_downloader-1.3.3.dist-info/RECORD
