Metadata-Version: 2.1
Name: vvvvid_downloader
Version: 1.3.3
Summary: Uno script in Python per scaricare da VVVVID. 
Home-page: https://github.com/nearata/vvvvid-downloader
Author: Nearata
Author-email: nearata@protonmail.com
Requires-Python: >=3.9
Classifier: License :: OSI Approved :: MIT License
Classifier: Programming Language :: Python :: 3
Classifier: Programming Language :: Python :: 3 :: Only
Classifier: Programming Language :: Python :: 3.9
Requires-Dist: inquirer ==3.1.3
Requires-Dist: httpx ==0.24.0
Requires-Dist: rich ==13.3.5
Requires-Dist: click ==8.1.3
Requires-Dist: h2 >=3,<5
